{
  "AI Environment Design": "KI-Umgebungsdesign",
  "Agent Memory & Protocols": "Agent-Memory & Protokolle",
  "Blog Infrastructure": "Blog-Infrastruktur",
  "Circuit Discovery": "Schaltkreis-Entdeckung",
  "Dream Engine Phases": "Dream-Engine-Phasen",
  "Dream Pipeline": "Dream-Pipeline",
  "Evolution Loop": "Evolutionsschleife",
  "Field Notes": "Feldnotizen",
  "Go Data Structures": "Go-Datenstrukturen",
  "Go Test Infrastructure": "Go-Test-Infrastruktur",
  "MCP Architecture": "MCP-Architektur",
  "MCP Toolset": "MCP-Werkzeuge",
  "Measurement Timing": "Messzeitpunkt",
  "Mutation Loop": "Mutationsschleife",
  "OAuth & MCP Auth": "OAuth & MCP-Auth",
  "Pure Awareness": "Reines Bewusstsein",
  "SAE Measurement": "SAE-Messung",
  "Waking State": "Wachzustand"
}
